branch_cleaner.py
gitbranch_clean-1.0.0.dist-info/licenses/LICENSE
gitbranch_clean-1.0.0.dist-info/METADATA
gitbranch_clean-1.0.0.dist-info/WHEEL
gitbranch_clean-1.0.0.dist-info/entry_points.txt
gitbranch_clean-1.0.0.dist-info/top_level.txt
gitbranch_clean-1.0.0.dist-info/RECORD
