Metadata-Version: 2.4
Name: gitbranch-clean
Version: 1.0.0
Summary: Delete merged git branches. That's it.
Home-page: https://github.com/yourusername/gitbranch-clean
Author: Justin Kindrix
Classifier: Programming Language :: Python :: 3
Classifier: License :: OSI Approved :: MIT License
Classifier: Operating System :: OS Independent
Requires-Python: >=3.6
License-File: LICENSE
Dynamic: author
Dynamic: classifier
Dynamic: description
Dynamic: description-content-type
Dynamic: home-page
Dynamic: license-file
Dynamic: requires-python
Dynamic: summary
